darwin/.DS_Store
darwin/__init__.py
darwin/backend_v2.py
darwin/cli.py
darwin/cli_functions.py
darwin/client.py
darwin/config.py
darwin/dataset/__init__.py
darwin/dataset/download_manager.py
darwin/dataset/identifier.py
darwin/dataset/local_dataset.py
darwin/dataset/release.py
darwin/dataset/remote_dataset.py
darwin/dataset/remote_dataset_v1.py
darwin/dataset/remote_dataset_v2.py
darwin/dataset/split_manager.py
darwin/dataset/upload_manager.py
darwin/dataset/utils.py
darwin/datatypes.py
darwin/doc_enum.py
darwin/exceptions.py
darwin/exporter/__init__.py
darwin/exporter/exporter.py
darwin/exporter/formats/__init__.py
darwin/exporter/formats/coco.py
darwin/exporter/formats/cvat.py
darwin/exporter/formats/darwin.py
darwin/exporter/formats/darwin_1_0.py
darwin/exporter/formats/dataloop.py
darwin/exporter/formats/instance_mask.py
darwin/exporter/formats/mask.py
darwin/exporter/formats/nifti.py
darwin/exporter/formats/numpy_encoder.py
darwin/exporter/formats/pascalvoc.py
darwin/exporter/formats/semantic_mask.py
darwin/exporter/formats/semantic_mask_grey.py
darwin/exporter/formats/semantic_mask_index.py
darwin/exporter/formats/yolo.py
darwin/importer/__init__.py
darwin/importer/formats/__init__.py
darwin/importer/formats/coco.py
darwin/importer/formats/csv_tags.py
darwin/importer/formats/csv_tags_video.py
darwin/importer/formats/darwin.py
darwin/importer/formats/dataloop.py
darwin/importer/formats/labelbox.py
darwin/importer/formats/labelbox_schemas.py
darwin/importer/formats/nifti.py
darwin/importer/formats/nifti_schemas.py
darwin/importer/formats/pascal_voc.py
darwin/importer/formats/superannotate.py
darwin/importer/formats/superannotate_schemas.py
darwin/importer/importer.py
darwin/item.py
darwin/item_sorter.py
darwin/options.py
darwin/path_utils.py
darwin/torch/__init__.py
darwin/torch/dataset.py
darwin/torch/transforms.py
darwin/torch/utils.py
darwin/utils.py
darwin/validators.py
darwin/version/__init__.py
darwin_pyproj_test-0.8.7.dist-info/LICENSE
darwin_pyproj_test-0.8.7.dist-info/WHEEL
darwin_pyproj_test-0.8.7.dist-info/entry_points.txt
darwin_pyproj_test-0.8.7.dist-info/METADATA
darwin_pyproj_test-0.8.7.dist-info/RECORD
