Metadata-Version: 2.1
Name: darwin-pyproj-test
Version: 0.8.7
Summary: Library and command line interface for darwin.v7labs.com
Home-page: https://docs.v7labs.com/reference/getting-started-2
License: MIT
Author: V7
Author-email: info@v7labs.com
Requires-Python: >=3.8.0,<3.11
Classifier: License :: OSI Approved :: MIT License
Classifier: Programming Language :: Python :: 3
Classifier: Programming Language :: Python :: 3.8
Classifier: Programming Language :: Python :: 3.9
Classifier: Programming Language :: Python :: 3.10
Classifier: Programming Language :: Python :: 3
Provides-Extra: dev
Provides-Extra: medical
Provides-Extra: ml
Provides-Extra: test
Requires-Dist: argcomplete (>=2.0.0,<3.0.0)
Requires-Dist: black[dev] (>=22.12.0,<23.0.0) ; extra == "dev"
Requires-Dist: connected-components-3d[medical] (>=3.10.3,<4.0.0) ; extra == "medical"
Requires-Dist: dataclasses (>=0.8,<0.9) ; python_version < "3.7"
Requires-Dist: debugpy[dev] (>=1.6.5,<2.0.0) ; extra == "dev"
Requires-Dist: deprecation (>=2.1.0,<3.0.0)
Requires-Dist: flake8-pyproject[dev,test] (>=1.2.2,<2.0.0) ; (python_full_version >= "3.8.1" and python_version < "3.11") and (extra == "dev" or extra == "test")
Requires-Dist: flake8[dev] (>=6.0.0,<7.0.0) ; (python_full_version >= "3.8.1" and python_version < "3.11") and (extra == "dev")
Requires-Dist: humanize (>=4.4.0,<5.0.0)
Requires-Dist: isort[dev] (>=5.11.4,<6.0.0) ; extra == "dev"
Requires-Dist: jsonschema (==3.2.0)
Requires-Dist: mypy[dev] (>=0.991,<0.992) ; extra == "dev"
Requires-Dist: nibabel[medical] (>=5.0.0,<6.0.0) ; extra == "medical"
Requires-Dist: numpy (<=1.23.0)
Requires-Dist: orjson (>=3.8.5,<4.0.0)
Requires-Dist: pillow (>=9.4.0,<10.0.0)
Requires-Dist: pydantic (>=1.10.4,<2.0.0)
Requires-Dist: pytest-describe[dev,test] (>=2.0.1,<3.0.0) ; extra == "dev" or extra == "test"
Requires-Dist: pytest[dev,test] (>=7.2.1,<8.0.0) ; extra == "dev" or extra == "test"
Requires-Dist: pyyaml (>=5.1)
Requires-Dist: requests (>=2.28.1,<3.0.0)
Requires-Dist: responses[dev,test] (>=0.22.0,<0.23.0) ; extra == "dev" or extra == "test"
Requires-Dist: rich (>=13.0.1,<14.0.0)
Requires-Dist: scikit-learn[ml,test] (>=1.2.0,<2.0.0) ; extra == "ml"
Requires-Dist: toml (>=0.10.2,<0.11.0)
Requires-Dist: torch[ml] (>=1.13.1,<2.0.0) ; extra == "ml"
Requires-Dist: torchvision[ml] (>=0.14.1,<0.15.0) ; extra == "ml"
Requires-Dist: upolygon (==0.1.8)
Project-URL: Documentation, https://darwin-py-sdk.v7labs.com/index.html
Project-URL: Repository, https://github.com/v7labs/darwin-py
